{
  "schemaVersion": 2,
  "pipelineVersion": "2.0.0",
  "catalogueVersion": 1,
  "previousCatalogueVersion": -1,
  "generatedAtMs": 1783242811953,
  "channelCount": 13891,
  "liveChannelCount": 13891,
  "providerCount": 8,
  "sourceCount": 18335,
  "artifacts": [
    {
      "name": "channels.json",
      "relativePath": "channels.json",
      "uncompressedBytes": 13181136,
      "compressedBytes": 13181136,
      "checksumSha256": "6c3da7c3f732519dea0944e5bd1048d6c99ba5eff18e635bf5b5aadaefc5c3ab",
      "checksumMd5": "abe9afb0f01aee3c14c4e9941290fe9e",
      "artifactType": "CHANNELS",
      "generatedAtMs": 1783242811009
    },
    {
      "name": "channels.json.gz",
      "relativePath": "channels.json.gz",
      "uncompressedBytes": 13181136,
      "compressedBytes": 1456256,
      "checksumSha256": "f15e54794efca9afe7a0fc7a8cb4f25c9f7ac94f2b32eaabfc42b8001e880e52",
      "checksumMd5": "ff94e33bf75f47faddeb2035b66d3752",
      "artifactType": "CHANNELS",
      "generatedAtMs": 1783242811206
    },
    {
      "name": "live_channels.json",
      "relativePath": "live_channels.json",
      "uncompressedBytes": 13181136,
      "compressedBytes": 13181136,
      "checksumSha256": "6c3da7c3f732519dea0944e5bd1048d6c99ba5eff18e635bf5b5aadaefc5c3ab",
      "checksumMd5": "abe9afb0f01aee3c14c4e9941290fe9e",
      "artifactType": "LIVE_CHANNELS",
      "generatedAtMs": 1783242811440
    },
    {
      "name": "live_channels.json.gz",
      "relativePath": "live_channels.json.gz",
      "uncompressedBytes": 13181136,
      "compressedBytes": 1456256,
      "checksumSha256": "f15e54794efca9afe7a0fc7a8cb4f25c9f7ac94f2b32eaabfc42b8001e880e52",
      "checksumMd5": "ff94e33bf75f47faddeb2035b66d3752",
      "artifactType": "LIVE_CHANNELS",
      "generatedAtMs": 1783242811638
    },
    {
      "name": "search_index.json",
      "relativePath": "search_index.json",
      "uncompressedBytes": 4598881,
      "compressedBytes": 4598881,
      "checksumSha256": "754c2237300fa79d339cb46c9cb1537a9caaa2483529fca273da5b42d84fb944",
      "checksumMd5": "9fc95ba466f3fb68a8a15b16d507dafe",
      "artifactType": "SEARCH_INDEX",
      "generatedAtMs": 1783242811763
    },
    {
      "name": "search_index.json.gz",
      "relativePath": "search_index.json.gz",
      "uncompressedBytes": 4598881,
      "compressedBytes": 618501,
      "checksumSha256": "15ec4831066146879e7cc419a3690b1d8f8c4ffedc40ec1fe574b5cea6986f6e",
      "checksumMd5": "e1e60e91571b0e8a5303c751920c276d",
      "artifactType": "SEARCH_INDEX",
      "generatedAtMs": 1783242811849
    },
    {
      "name": "categories.json",
      "relativePath": "categories.json",
      "uncompressedBytes": 439568,
      "compressedBytes": 439568,
      "checksumSha256": "68f37f69eda765c93764ec12e26a7dfde41c53d939eb656b29e84f3355e01ff4",
      "checksumMd5": "756d80d8b3ee4e7f389c1aeb54636540",
      "artifactType": "CATEGORIES",
      "generatedAtMs": 1783242811865
    },
    {
      "name": "categories.json.gz",
      "relativePath": "categories.json.gz",
      "uncompressedBytes": 439568,
      "compressedBytes": 115460,
      "checksumSha256": "ddde0dbd9b584cdaacd1ea6475aaaf5c78680a572098fcbcd9f2160599cf372e",
      "checksumMd5": "77571efcc6b946895b3a85e9ce4babe1",
      "artifactType": "CATEGORIES",
      "generatedAtMs": 1783242811876
    },
    {
      "name": "regions.json",
      "relativePath": "regions.json",
      "uncompressedBytes": 377186,
      "compressedBytes": 377186,
      "checksumSha256": "12a82435b934096834b2a7892cea86d214b6855fb694e0aa979eb1968fb2b348",
      "checksumMd5": "eb70123dde6b7c02923e3500b1c32311",
      "artifactType": "REGIONS",
      "generatedAtMs": 1783242811890
    },
    {
      "name": "regions.json.gz",
      "relativePath": "regions.json.gz",
      "uncompressedBytes": 377186,
      "compressedBytes": 89710,
      "checksumSha256": "cbd6e4508a279fe68434f28856f80c043c678e1e5e50e373324a4669c326ff16",
      "checksumMd5": "ff5957a43fafaf86cae0a0bb793add62",
      "artifactType": "REGIONS",
      "generatedAtMs": 1783242811899
    },
    {
      "name": "recommendations.json",
      "relativePath": "recommendations.json",
      "uncompressedBytes": 42191,
      "compressedBytes": 42191,
      "checksumSha256": "6b7002ee1c3c99164bf11e5d15018468b2db1587b836dbdae8249ea22177a622",
      "checksumMd5": "e0bff528611b988b94a29814a3e2bf4b",
      "artifactType": "RECOMMENDATIONS",
      "generatedAtMs": 1783242811918
    },
    {
      "name": "recommendations.json.gz",
      "relativePath": "recommendations.json.gz",
      "uncompressedBytes": 42191,
      "compressedBytes": 11856,
      "checksumSha256": "216360b5f1569d30c7cdb378cd5e9814c4f6b37d14412b2f6e421040de796df6",
      "checksumMd5": "e0d5dbc5f182cc2279b156cece06420a",
      "artifactType": "RECOMMENDATIONS",
      "generatedAtMs": 1783242811919
    },
    {
      "name": "providers.json",
      "relativePath": "providers.json",
      "uncompressedBytes": 1161,
      "compressedBytes": 1161,
      "checksumSha256": "a774c607255056b866e4cac488a47a60ce8b6a3c5b962d0fbdf837586155b76f",
      "checksumMd5": "2c4fb90e16e90cc56f931b5f696f44a2",
      "artifactType": "PROVIDERS",
      "generatedAtMs": 1783242811939
    },
    {
      "name": "providers.json.gz",
      "relativePath": "providers.json.gz",
      "uncompressedBytes": 1161,
      "compressedBytes": 264,
      "checksumSha256": "e888eb77d0d05ff534c70c766d802c41454f43ed6335e222167cde9fe2cdef2b",
      "checksumMd5": "38a0ce223100e905c0c459916d8d3edb",
      "artifactType": "PROVIDERS",
      "generatedAtMs": 1783242811940
    },
    {
      "name": "featured.json",
      "relativePath": "featured.json",
      "uncompressedBytes": 24531,
      "compressedBytes": 24531,
      "checksumSha256": "54cd174af0fa76e2efe78ca83b7446200727a9faf458378a2553cfc5fdd09fbd",
      "checksumMd5": "80fe886c100ae7f84fa75fbbc7888452",
      "artifactType": "FEATURED",
      "generatedAtMs": 1783242811947
    },
    {
      "name": "featured.json.gz",
      "relativePath": "featured.json.gz",
      "uncompressedBytes": 24531,
      "compressedBytes": 3626,
      "checksumSha256": "de396ae973650b6a708ecb2517a3589253339c73d1b6bad5d0a5a9b8043345fe",
      "checksumMd5": "1d19a9f111e000331e49f381f0ddf675",
      "artifactType": "FEATURED",
      "generatedAtMs": 1783242811948
    },
    {
      "name": "aliases.json",
      "relativePath": "aliases.json",
      "uncompressedBytes": 2,
      "compressedBytes": 2,
      "checksumSha256": "44136fa355b3678a1146ad16f7e8649e94fb4fc21fe77e8310c060f61caaff8a",
      "checksumMd5": "99914b932bd37a50b983c5e7c90ae93b",
      "artifactType": "ALIASES",
      "generatedAtMs": 1783242811951
    },
    {
      "name": "aliases.json.gz",
      "relativePath": "aliases.json.gz",
      "uncompressedBytes": 2,
      "compressedBytes": 22,
      "checksumSha256": "15a60fe9599316b767a8b8be4d0141d2445efdcb8290884c3ee08b162d404981",
      "checksumMd5": "dd2045819bcb94721bb3ae1ade179aa0",
      "artifactType": "ALIASES",
      "generatedAtMs": 1783242811951
    }
  ],
  "integrity": {
    "rootHash": "",
    "signed": false,
    "signature": ""
  },
  "changelog": ""
}